{
  "ogmoVersion": "3.3.0",
  "width": 560,
  "height": 4096,
  "offsetX": 0,
  "offsetY": 0,
  "layers": [
    {
      "name": "Track",
      "_eid": "83685188",
      "offsetX": 0,
      "offsetY": -104,
      "gridCellWidth": 80,
      "gridCellHeight": 140,
      "gridCellsX": 7,
      "gridCellsY": 30,
      "tileset": "track ",
      "data": [0, -1, -1, -1, -1, -1, 1, 0, -1, -1, -1, -1, -1, 1, 6, -1, -1, -1, -1, -1, 7, 8, -1, -1, -1, -1, -1, 15, 22, -1, -1, -1, -1, -1, 23, 6, -1, -1, -1, -1, -1, 7, 8, -1, -1, -1, -1, -1, 15, 22, -1, -1, -1, -1, -1, 23, 6, -1, -1, -1, -1, -1, 7, 8, -1, -1, -1, -1, -1, 15, 22, -1, -1, -1, -1, -1, 23, 6, -1, -1, -1, -1, -1, 7, 8, -1, -1, -1, -1, -1, 15, 22, -1, 0, -1, 0, -1, 23, 6, -1, 0, 96, 0, -1, 1, 8, -1, -1, 97, -1, -1, 7, 22, -1, -1, 97, -1, -1, 15, 6, -1, -1, 97, -1, -1, 23, 8, -1, -1, 97, -1, -1, 7, 22, -1, -1, 98, -1, -1, 15, 0, -1, -1, -1, 0, -1, 23, 6, -1, -1, -1, -1, -1, 7, 93, -1, -1, -1, -1, -1, 90, 52, 53, -1, -1, -1, 50, 51, 2, 3, -1, -1, -1, 4, 5, -1, 65, -1, -1, -1, 62, -1, -1, 22, -1, -1, -1, 23, -1, -1, 6, -1, -1, -1, 7, -1, -1, 64, -1, -1, -1, 63, -1, -1, 22, -1, -1, -1, 23, -1],
      "exportMode": 0,
      "arrayMode": 0
    },
    {
      "name": "lanesAndLines",
      "_eid": "84427515",
      "offsetX": 0,
      "offsetY": 0,
      "gridCellWidth": 80,
      "gridCellHeight": 140,
      "gridCellsX": 7,
      "gridCellsY": 31,
      "tileset": "track ",
      "data": [-1, 17, -1, -1, -1, 16, -1, -1, 17, -1, -1, -1, 16, -1, -1, 38, 45, 45, 45, 39, -1, -1, 17, -1, -1, -1, 16, -1, -1, 17, -1, -1, -1, 16, -1, -1, 38, 45, 45, 45, 39, -1, -1, 17, -1, -1, -1, 16, -1, -1, 17, -1, -1, -1, 16, -1, -1, 38, 45, 45, 45, 39, -1, -1, 17, -1, -1, -1, 16, -1, -1, 17, -1, -1, -1, 16, -1, -1, 38, 45, 45, 45, 39, -1, -1, 17, -1, -1, -1, 16, -1, -1, 17, 99, 100, 101, 16, -1, -1, 38, 121, -1, 120, 39, -1, -1, 17, 16, -1, 17, 16, -1, -1, 17, 16, -1, 17, 16, -1, -1, 38, 39, -1, 38, 39, -1, -1, 17, 16, -1, 17, 16, -1, -1, 17, 105, -1, 104, 16, -1, -1, 38, 115, 102, 114, 39, -1, -1, 17, -1, -1, -1, 16, -1, -1, 17, -1, -1, -1, 16, -1, -1, -1, 72, 45, 80, -1, -1, -1, -1, 31, -1, 24, -1, -1, -1, -1, 17, -1, 16, -1, -1, -1, -1, 38, 45, 39, -1, -1, -1, -1, 17, -1, 16, -1, -1, -1, -1, 17, -1, 16, -1, -1, -1, -1, 38, 45, 39, -1, -1],
      "exportMode": 0,
      "arrayMode": 0
    }
  ]
}